CHANGELOG.rst
LICENSE
MANIFEST.in
README.rst
gilmsg.py
setup.py
gilmsg.egg-info/PKG-INFO
gilmsg.egg-info/SOURCES.txt
gilmsg.egg-info/dependency_links.txt
gilmsg.egg-info/entry_points.txt
gilmsg.egg-info/not-zip-safe
gilmsg.egg-info/pbr.json
gilmsg.egg-info/requires.txt
gilmsg.egg-info/top_level.txt