Metadata-Version: 1.0
Name: gilmsg
Version: 0.1.2
Summary: A reliability layer on top of fedmsg
Home-page: https://github.com/fedora-infra/gilmsg/
Author: Ralph Bean
Author-email: rbean@redhat.com
License: LGPLv2+
Platform: UNKNOWN
